cobweb/__init__.py
cobweb/engine.py
cobweb/model.py
cobweb/activations/__init__.py
cobweb/activations/relu_activation.py
cobweb/activations/softmax_activation.py
cobweb/activations/tanh_activation.py
cobweb/losses/R2.py
cobweb/losses/__init__.py
cobweb/losses/cross_entropy_loss.py
cobweb/losses/mae.py
cobweb/losses/mse.py
cubweb-0.1.6.dist-info/LICENSE
cubweb-0.1.6.dist-info/METADATA
cubweb-0.1.6.dist-info/WHEEL
cubweb-0.1.6.dist-info/top_level.txt
cubweb-0.1.6.dist-info/RECORD
